[
  {
    "name": "John P. Hodkinson",
    "positions": [
      "Mayor"
    ],
    "email": "John.Hodkinson@uniongapwa.gov"
  },
  {
    "name": "Roger Wentz",
    "positions": [
      "Deputy Mayor"
    ],
    "email": "Roger.Wentz@uniongapwa.gov"
  },
  {
    "name": "Sandy Dailey",
    "positions": [
      "Councilmember"
    ],
    "email": "Sandy.Dailey@uniongapwa.gov"
  },
  {
    "name": "Carol Fredrickson",
    "positions": [
      "Councilmember"
    ],
    "email": "Carol.Fredrickson@uniongapwa.gov"
  },
  {
    "name": "Jack Galloway",
    "positions": [
      "Councilmember"
    ],
    "email": "Jack.Galloway@uniongapwa.gov"
  },
  {
    "name": "Julie Schilling",
    "positions": [
      "Councilmember"
    ],
    "email": "Julie.Schilling@uniongapwa.gov"
  },
  {
    "name": "Greg Sewell",
    "positions": [
      "Councilmember"
    ],
    "email": "Greg.sewell@uniongapwa.gov"
  },
  {
    "name": "Sharon  Bounds",
    "positions": [
      "City Manager"
    ],
    "email": "sharon.bounds@uniongapwa.gov"
  },
  {
    "name": "Jason Cavanaugh",
    "positions": [
      "Community Development/Public Works Director"
    ],
    "email": "jason.cavanaugh@uniongapwa.gov"
  },
  {
    "name": "Lynette Bisconer",
    "positions": [
      "Finance/Administration Director"
    ],
    "email": "lynette.bisconer@uniongapwa.gov"
  },
  {
    "name": "Greg Cobb",
    "positions": [
      "Police Chief"
    ],
    "email": null
  }
]