[
  {
    "name": "Drew Florence",
    "image": null,
    "positions": [
      "Assistant City Manager"
    ],
    "email": null,
    "phone_number": null,
    "website": null,
    "sources": null,
    "start_term_date": null,
    "end_term_date": null
  },
  {
    "name": "Heather Kintzley",
    "image": null,
    "positions": [
      "City Attorney"
    ],
    "email": null,
    "phone_number": null,
    "website": null,
    "sources": null,
    "start_term_date": null,
    "end_term_date": null
  },
  {
    "name": "Jennifer Rogers",
    "image": null,
    "positions": [
      "City Clerk"
    ],
    "email": null,
    "phone_number": null,
    "website": null,
    "sources": null,
    "start_term_date": null,
    "end_term_date": null
  },
  {
    "name": "Jon Amundson",
    "image": null,
    "positions": [
      "City Manager"
    ],
    "email": null,
    "phone_number": null,
    "website": null,
    "sources": null,
    "start_term_date": null,
    "end_term_date": null
  },
  {
    "name": "Hollie Alexander",
    "image": null,
    "positions": [
      "Communications/marketing Manager"
    ],
    "email": null,
    "phone_number": null,
    "website": null,
    "sources": null,
    "start_term_date": null,
    "end_term_date": null
  },
  {
    "name": "Jhoanna  Jones",
    "image": null,
    "positions": [
      "Council Member"
    ],
    "email": null,
    "phone_number": null,
    "website": null,
    "sources": null,
    "start_term_date": null,
    "end_term_date": null
  },
  {
    "name": "Ryan  Lukson",
    "image": null,
    "positions": [
      "Council Member"
    ],
    "email": null,
    "phone_number": null,
    "website": null,
    "sources": null,
    "start_term_date": null,
    "end_term_date": null
  },
  {
    "name": "Kurt Maier",
    "image": null,
    "positions": [
      "Council Member"
    ],
    "email": null,
    "phone_number": null,
    "website": null,
    "sources": null,
    "start_term_date": null,
    "end_term_date": null
  },
  {
    "name": "Shane  VanDyke",
    "image": null,
    "positions": [
      "Council Member"
    ],
    "email": null,
    "phone_number": null,
    "website": null,
    "sources": null,
    "start_term_date": null,
    "end_term_date": null
  },
  {
    "name": "Ryan Whitten",
    "image": null,
    "positions": [
      "Council Member"
    ],
    "email": null,
    "phone_number": null,
    "website": null,
    "sources": null,
    "start_term_date": null,
    "end_term_date": null
  },
  {
    "name": "Sandra Kent",
    "image": null,
    "positions": [
      "Councilmember (mpt)"
    ],
    "email": null,
    "phone_number": null,
    "website": null,
    "sources": null,
    "start_term_date": null,
    "end_term_date": null
  },
  {
    "name": "Joe Schiessl",
    "image": null,
    "positions": [
      "Deputy City Manager"
    ],
    "email": null,
    "phone_number": null,
    "website": null,
    "sources": null,
    "start_term_date": null,
    "end_term_date": null
  },
  {
    "name": "Clint Whitney",
    "image": null,
    "positions": [
      "Energy Services Manager"
    ],
    "email": null,
    "phone_number": null,
    "website": null,
    "sources": null,
    "start_term_date": null,
    "end_term_date": null
  },
  {
    "name": "Felicia Siefken",
    "image": null,
    "positions": [
      "Executive Assistant To City Manager Office"
    ],
    "email": null,
    "phone_number": null,
    "website": null,
    "sources": null,
    "start_term_date": null,
    "end_term_date": null
  },
  {
    "name": "Brandon Allen",
    "image": null,
    "positions": [
      "Finance Director"
    ],
    "email": null,
    "phone_number": null,
    "website": null,
    "sources": null,
    "start_term_date": null,
    "end_term_date": null
  },
  {
    "name": "Tom Huntington",
    "image": null,
    "positions": [
      "Fire/emergency Services Director"
    ],
    "email": null,
    "phone_number": null,
    "website": null,
    "sources": null,
    "start_term_date": null,
    "end_term_date": null
  },
  {
    "name": "Lacey  Paulsen",
    "image": null,
    "positions": [
      "Human Resources Manager"
    ],
    "email": null,
    "phone_number": null,
    "website": null,
    "sources": null,
    "start_term_date": null,
    "end_term_date": null
  },
  {
    "name": "Deepti  Vijayan",
    "image": null,
    "positions": [
      "Information Technology Manager"
    ],
    "email": null,
    "phone_number": null,
    "website": null,
    "sources": null,
    "start_term_date": null,
    "end_term_date": null
  },
  {
    "name": "Joe Schiessl",
    "image": null,
    "positions": [
      "Interim Development Services Director"
    ],
    "email": null,
    "phone_number": null,
    "website": null,
    "sources": null,
    "start_term_date": null,
    "end_term_date": null
  },
  {
    "name": "Christopher  Nulph",
    "image": null,
    "positions": [
      "Library Manager"
    ],
    "email": null,
    "phone_number": null,
    "website": null,
    "sources": null,
    "start_term_date": null,
    "end_term_date": null
  },
  {
    "name": "Theresa  Richardson",
    "image": null,
    "positions": [
      "Mayor"
    ],
    "email": null,
    "phone_number": null,
    "website": null,
    "sources": null,
    "start_term_date": null,
    "end_term_date": null
  },
  {
    "name": "Mike Stevens",
    "image": null,
    "positions": [
      "Planning Manager"
    ],
    "email": null,
    "phone_number": null,
    "website": null,
    "sources": null,
    "start_term_date": null,
    "end_term_date": null
  },
  {
    "name": "Brigit Clary",
    "image": null,
    "positions": [
      "Police Chief"
    ],
    "email": null,
    "phone_number": null,
    "website": null,
    "sources": null,
    "start_term_date": null,
    "end_term_date": null
  },
  {
    "name": "Toni Fulton",
    "image": null,
    "positions": [
      "Public Records Officer"
    ],
    "email": null,
    "phone_number": null,
    "website": null,
    "sources": null,
    "start_term_date": null,
    "end_term_date": null
  },
  {
    "name": "Pete Rogalsky",
    "image": null,
    "positions": [
      "Public Works Director"
    ],
    "email": null,
    "phone_number": null,
    "website": null,
    "sources": null,
    "start_term_date": null,
    "end_term_date": null
  }
]