[
  {
    "name": "David Olson",
    "positions": [
      "Mayor"
    ],
    "email": "mayor@cityofedgewood.org"
  },
  {
    "name": "Rosanne Tomyn",
    "positions": [
      "Deputy Mayor"
    ],
    "email": "rosanne.tomyn@cityofedgewood.org"
  },
  {
    "name": "Erica  Buckley",
    "positions": [
      "Councilmember"
    ],
    "email": null
  },
  {
    "name": "Christi  Keith",
    "positions": [
      "Councilmember"
    ],
    "email": null
  },
  {
    "name": "Jennifer  Pazaruski",
    "positions": [
      "Councilmember"
    ],
    "email": "jennifer.pazaruski@cityofedgewood.org"
  },
  {
    "name": "Jason Ramirez",
    "positions": [
      "Councilmember"
    ],
    "email": "jason.ramirez@cityofedgewood.org"
  },
  {
    "name": "Jeff Southard",
    "positions": [
      "Councilmember"
    ],
    "email": "jeff.southard@cityofedgewood.org"
  },
  {
    "name": "John C.  West",
    "positions": [
      "Councilmember"
    ],
    "email": "jwest@cityofedgewood.org"
  },
  {
    "name": "Stephanie Goff",
    "positions": [
      "Accounting Manager"
    ],
    "email": "stephanie@cityofedgewood.org"
  },
  {
    "name": "Rachel Pitzel",
    "positions": [
      "Assistant City Administrator"
    ],
    "email": "rachel@cityofedgewood.org"
  },
  {
    "name": "James  Tumelson",
    "positions": [
      "Building Official"
    ],
    "email": "james@cityofedgewood.org"
  },
  {
    "name": "Jill Schwerzler-Herrera",
    "positions": [
      "City Clerk/Human Resources Director"
    ],
    "email": "jill@cityofedgewood.org"
  },
  {
    "name": "Jeremy Metzler",
    "positions": [
      "Community Development Director"
    ],
    "email": "jeremy@cityofedgewood.org"
  },
  {
    "name": "Hardeep Goraya",
    "positions": [
      "Finance Director"
    ],
    "email": "hardeep@cityofedgewood.org"
  },
  {
    "name": "Jennifer Bartelson",
    "positions": [
      "Office Manager"
    ],
    "email": "jennifer@cityofedgewood.org"
  },
  {
    "name": "Jason Youngman",
    "positions": [
      "Police Chief"
    ],
    "email": null
  },
  {
    "name": "Chuck Hendricksen",
    "positions": [
      "Public Works Director"
    ],
    "email": "chuck@cityofedgewood.org"
  }
]