[
  {
    "name": "David Rafferty",
    "positions": [
      "Mayor"
    ],
    "email": "mayor@fairfieldwa.com"
  },
  {
    "name": "Alisha Anderson",
    "positions": [
      "Councilmember"
    ],
    "email": "councilposition1@fairfieldwa.com"
  },
  {
    "name": "Amanda Blood",
    "positions": [
      "Councilmember"
    ],
    "email": "councilposition5@fairfieldwa.com"
  },
  {
    "name": "Josh Boyd",
    "positions": [
      "Councilmember"
    ],
    "email": null
  },
  {
    "name": "Brady Collinson",
    "positions": [
      "Councilmember"
    ],
    "email": "councilposition2@fairfieldwa.com"
  },
  {
    "name": "Bill Enzler",
    "positions": [
      "Councilmember"
    ],
    "email": "councilposition4@fairfieldwa.com"
  },
  {
    "name": "Devin Billington",
    "positions": [
      "Public Works Director"
    ],
    "email": "Publicworks@FairfieldWA.com"
  },
  {
    "name": "Jared Harward",
    "positions": [
      "Town Clerk/Treasurer"
    ],
    "email": "townclerk@fairfieldwa.com"
  }
]