[
  {
    "name": "Becky Gallien",
    "positions": [
      "Management Analyst"
    ],
    "email": "beckyg@woodvillageor.gov",
    "phone_number": "(503) 489-6852"
  },
  {
    "name": "Caroline Hinders",
    "positions": [
      "Community Outreach and Engagement"
    ],
    "email": "CarolineH@woodvillageor.gov",
    "phone_number": "(503) 667-6211"
  },
  {
    "name": "Catherine Johnston",
    "positions": [
      "Parks Commission"
    ],
    "email": "city@woodvillageor.gov",
    "phone_number": "(503) 667-6211"
  },
  {
    "name": "Chelsea Slaughter",
    "positions": [
      "Utility Billing"
    ],
    "email": "ChelseaS@woodvillageor.gov",
    "phone_number": "(503) 489-6851"
  },
  {
    "name": "Dara Tan",
    "positions": [
      "Councilor"
    ],
    "email": "DaraT@woodvillageor.gov",
    "phone_number": "(503) 667-6211"
  },
  {
    "name": "Erika  Normine",
    "positions": [
      "Public Works Supervisor"
    ],
    "email": "ErikaN@woodvillageor.gov",
    "phone_number": "(503) 667-6211"
  },
  {
    "name": "Garrett Winterbottom",
    "positions": [
      "Utility Worker II"
    ],
    "email": "garrettw@woodvillageor.gov",
    "phone_number": "(503) 667-6211"
  },
  {
    "name": "Greg Dirks",
    "positions": [
      "City Manager"
    ],
    "email": "gregd@woodvillageor.gov",
    "phone_number": "(503) 489-6854"
  },
  {
    "name": "Jairo Rios-Campos",
    "positions": [
      "Mayor"
    ],
    "email": "jairorc@woodvillageor.gov",
    "phone_number": "(503) 667-6211"
  },
  {
    "name": "Jeremy Charpentier",
    "positions": [
      "Utility Worker I"
    ],
    "email": "JeremyC@woodvillageor.gov",
    "phone_number": "(503) 667-6211"
  },
  {
    "name": "Jim Mott",
    "positions": [
      "Planning Commission Chair/Parks Commission Chair/Design Review Board Chair"
    ],
    "email": "city@woodvillageor.gov",
    "phone_number": "(503) 667-6211"
  },
  {
    "name": "John Miner",
    "positions": [
      "Councilor"
    ],
    "email": "JohnM@WoodVillageOR.gov",
    "phone_number": "(503) 667-6211"
  },
  {
    "name": "Kevin Holstad",
    "positions": [
      "Utility Worker II"
    ],
    "email": "kevinh@woodvillageor.gov",
    "phone_number": "(503) 667-6211"
  },
  {
    "name": "Kyler  Roberts",
    "positions": [
      "Engineering Technician"
    ],
    "email": "KylerR@WoodVillageOR.gov",
    "phone_number": "(503) 489-6862"
  },
  {
    "name": "Linda Jensen",
    "positions": [
      "Planning Commissioner/Design Review Board"
    ],
    "email": "city@woodvillageor.gov",
    "phone_number": "(503) 667-6211"
  },
  {
    "name": "Lindsay Rivas",
    "positions": [
      "Accounts Payable"
    ],
    "email": "lindsayr@woodvillageor.gov",
    "phone_number": "(503) 667-6211"
  },
  {
    "name": "Mark Clark",
    "positions": [
      "Councilor"
    ],
    "email": "MarkC@woodvillageor.gov",
    "phone_number": "(503) 667-6211"
  },
  {
    "name": "Mary Clark",
    "positions": [
      "Parks Commission"
    ],
    "email": "city@woodvillageor.gov",
    "phone_number": "(503) 667-6211"
  },
  {
    "name": "Mary Dong",
    "positions": [
      "Building Permits & Code Enforcement"
    ],
    "email": "MaryD@woodvillageor.gov",
    "phone_number": "(503) 489-6861"
  },
  {
    "name": "Melissa Cervantes",
    "positions": [
      "PW Admin"
    ],
    "email": "MelissaC@woodvillageor.gov",
    "phone_number": "(503) 667-6211"
  },
  {
    "name": "Patricia Smith",
    "positions": [
      "Councilor"
    ],
    "email": "city@woodvillageor.gov",
    "phone_number": "(503) 667-6211"
  },
  {
    "name": "Robbie Betthauser",
    "positions": [
      "Groundskeeper"
    ],
    "email": "RobbieB@woodvillageor.gov",
    "phone_number": "(503) 667-6211"
  },
  {
    "name": "Seth Reeser",
    "positions": [
      "Finance Director"
    ],
    "email": "SethR@WoodVillageOR.gov",
    "phone_number": "(503) 489-6855"
  },
  {
    "name": "Stanley Dirks",
    "positions": [
      "Urban Renewal Vice Chair/Budget Committee"
    ],
    "email": "city@woodvillageor.gov",
    "phone_number": "(503) 667-6211"
  },
  {
    "name": "Yelena Shapovalov",
    "positions": [
      "Accountant"
    ],
    "email": "YelenaS@WoodVillageOR.gov",
    "phone_number": "(503) 489-6853"
  }
]