[
  {
    "name": "Julie Struck",
    "positions": [
      "Mayor"
    ],
    "email": "julie.struck@southbend-wa.gov"
  },
  {
    "name": "Patricia  Corcoran",
    "positions": [
      "Councilmember"
    ],
    "email": "patricia.corcoran@southbend-wa.gov"
  },
  {
    "name": "Jan Davis",
    "positions": [
      "Councilmember"
    ],
    "email": "jan.davis@southbend-wa.gov"
  },
  {
    "name": "Wyatt  Kuiken",
    "positions": [
      "Councilmember"
    ],
    "email": "wyatt.kuiken@southbend-wa.gov"
  },
  {
    "name": "Darren Manlow",
    "positions": [
      "Councilmember"
    ],
    "email": "darren.manlow@southbend-wa.gov"
  },
  {
    "name": "Clarence (Bunny) Willliams",
    "positions": [
      "Councilmember"
    ],
    "email": "clarence.williams@southbend-wa.gov"
  },
  {
    "name": "Michael Tierney",
    "positions": [
      "City Attorney"
    ],
    "email": "tierney@tierneylaw.com"
  },
  {
    "name": "David Johnson",
    "positions": [
      "City Clerk/Treasurer"
    ],
    "email": "david.johnson@southbend-wa.gov"
  },
  {
    "name": "Dennis  Houk",
    "positions": [
      "City Supervisor/Building Official"
    ],
    "email": "dennis.houk@southbend-wa.gov"
  },
  {
    "name": "Lucas Stigall",
    "positions": [
      "Police Chief"
    ],
    "email": "lucas.stigall@southbend-wa.gov"
  }
]