[
  {
    "name": "Douglas Whittlesey",
    "positions": [
      "Mayor",
      "Council Member"
    ],
    "updated_at": "2025-05-22"
  },
  {
    "name": "Chris Simon",
    "positions": [
      "Council Member"
    ],
    "updated_at": "2025-05-22"
  },
  {
    "name": "Devin R. Wilkie",
    "positions": [
      "Council Member"
    ],
    "updated_at": "2025-05-22"
  },
  {
    "name": "Erling Heistad",
    "positions": [
      "Council Member"
    ],
    "updated_at": "2025-05-22"
  },
  {
    "name": "George Sykes",
    "positions": [
      "Council Member"
    ],
    "updated_at": "2025-05-22"
  },
  {
    "name": "Karen Zook",
    "positions": [
      "Council Member"
    ],
    "updated_at": "2025-05-22"
  },
  {
    "name": "Laurel Stavis",
    "positions": [
      "Council Member"
    ],
    "updated_at": "2025-05-22"
  },
  {
    "name": "Nicole Ford Burley",
    "positions": [
      "Council Member"
    ],
    "updated_at": "2025-05-22"
  },
  {
    "name": "Timothy J. McNamara",
    "positions": [
      "Council Member"
    ],
    "updated_at": "2025-05-22"
  }
]