[
  {
    "name": "Amy Grabinski",
    "positions": [
      "Councilor"
    ],
    "email": "jennifer@cityofyoncalla.com",
    "phone_number": "(541) 849-2152"
  },
  {
    "name": "Bryce Wertz",
    "positions": [
      "Councilor"
    ],
    "email": "",
    "phone_number": "(541) 849-2152"
  },
  {
    "name": "Gene Vroman",
    "positions": [
      "Councilor"
    ],
    "email": "genevroman@yahoo.com",
    "phone_number": "(541) 680-2129"
  },
  {
    "name": "Harold Gilpin",
    "positions": [
      "Councilor"
    ],
    "email": "hgilpin24@yahoo.com",
    "phone_number": "(541) 849-2152"
  },
  {
    "name": "Jennifer  Bragg",
    "positions": [
      "City Administrator"
    ],
    "email": "jennifer@cityofyoncalla.com",
    "phone_number": "(541) 849-2152"
  },
  {
    "name": "Kathleen Wertz",
    "positions": [
      "Mayor"
    ],
    "email": "Mayor@cityofyoncalla.com",
    "phone_number": "(541) 849-2152"
  },
  {
    "name": "Sandra Harbaugh",
    "positions": [
      "Planning Director"
    ],
    "email": "sandra@cityofyoncalla.com",
    "phone_number": "(541) 849-2152"
  }
]